docs/source/conf.py
evokit/__init__.py
evokit/py.typed
evokit/_utils/dependency.py
evokit/_utils/inspect.py
evokit/core/__init__.py
evokit/core/algorithm.py
evokit/core/evaluator.py
evokit/core/population.py
evokit/core/selector.py
evokit/core/variator.py
evokit/core/accelerator/__init__.py
evokit/core/accelerator/parallelisers.py
evokit/evolvables/__init__.py
evokit/evolvables/_common.py
evokit/evolvables/algorithms.py
evokit/evolvables/bitstring.py
evokit/evolvables/funcs.py
evokit/evolvables/gp.py
evokit/evolvables/gp_visualiser.py
evokit/evolvables/lgp.py
evokit/evolvables/prefabs.py
evokit/evolvables/selectors.py
evokit/tools/__init__.py
evokit/tools/diversity/__init__.py
evokit/tools/lineage/__init__.py
evokit/watch/__init__.py
evokit/watch/memory.py
evokit/watch/visual.py
evokit/watch/watcher.py
evokit/watch/watchers.py
stash/okay.py
stash/test.py
evokit-1.1.0.dist-info/METADATA
evokit-1.1.0.dist-info/WHEEL
evokit-1.1.0.dist-info/top_level.txt
evokit-1.1.0.dist-info/RECORD
