Metadata-Version: 2.4
Name: evokit
Version: 1.1.0
Summary: An evolutionary computing framework.
Author-email: Yiding Li <commit@lyodine.com>
Project-URL: Documentation, https://yidingli.com/docs/evokit/
Project-URL: Repository, https://yidingli.com/projects/evokit/
Keywords: Machine Learning,Evolutionary Computing,Framework
Classifier: Development Status :: 5 - Production/Stable
Classifier: Intended Audience :: Developers
Classifier: Intended Audience :: Science/Research
Classifier: Programming Language :: Python :: 3.12
Classifier: Topic :: Scientific/Engineering :: Artificial Intelligence
Classifier: Topic :: Scientific/Engineering :: Artificial Life
Classifier: Topic :: Software Development :: Libraries :: Python Modules
Classifier: Typing :: Typed
Requires-Python: >=3.12.0
Provides-Extra: full
Requires-Dist: graphviz>=0.20.3; extra == "full"
Requires-Dist: matplotlib>=3.10.1; extra == "full"
Requires-Dist: numpy>=1.26.4; extra == "full"
Requires-Dist: multiprocess>=0.70.18; extra == "full"
Requires-Dist: dill>=0.4.0; extra == "full"
Requires-Dist: guppy>=3.1.5; extra == "full"
Requires-Dist: pympler>=1.1; extra == "full"
Provides-Extra: gp-visual
Requires-Dist: graphviz>=0.20.3; extra == "gp-visual"
Provides-Extra: watch-visual
Requires-Dist: matplotlib>=3.10.1; extra == "watch-visual"
Provides-Extra: numpy
Requires-Dist: numpy>=1.26.4; extra == "numpy"
Provides-Extra: multiprocess
Requires-Dist: multiprocess>=0.70.18; extra == "multiprocess"
Provides-Extra: pickling
Requires-Dist: dill>=0.4.0; extra == "pickling"
Provides-Extra: watch-memory
Requires-Dist: guppy>=3.1.5; extra == "watch-memory"
Requires-Dist: pympler>=1.1; extra == "watch-memory"
Provides-Extra: test
Requires-Dist: pytest>=8.2.0; extra == "test"
Requires-Dist: nbmake>=1.5.4; extra == "test"
